s3bkt/__init__.py
s3bkt/clients.py
s3bkt/command.py
s3bkt/s3util.py
S3bkt-0.4.0.dist-info/LICENSE
S3bkt-0.4.0.dist-info/METADATA
S3bkt-0.4.0.dist-info/WHEEL
S3bkt-0.4.0.dist-info/entry_points.txt
S3bkt-0.4.0.dist-info/top_level.txt
S3bkt-0.4.0.dist-info/RECORD
